trytond/modules/akademy_matriculation/LICENSE
trytond/modules/akademy_matriculation/README.md
trytond/modules/akademy_matriculation/__init__.py
trytond/modules/akademy_matriculation/configuration.py
trytond/modules/akademy_matriculation/configuration.xml
trytond/modules/akademy_matriculation/configuration_data.xml
trytond/modules/akademy_matriculation/matriculation.py
trytond/modules/akademy_matriculation/matriculation.xml
trytond/modules/akademy_matriculation/party.py
trytond/modules/akademy_matriculation/report.py
trytond/modules/akademy_matriculation/report.xml
trytond/modules/akademy_matriculation/tryton.cfg
trytond/modules/akademy_matriculation/locale/en.po
trytond/modules/akademy_matriculation/locale/fr.po
trytond/modules/akademy_matriculation/locale/pt.po
trytond/modules/akademy_matriculation/reports/application_criteria.fodt
trytond/modules/akademy_matriculation/reports/applications_result.fodt
trytond/modules/akademy_matriculation/reports/candidate.fodt
trytond/modules/akademy_matriculation/reports/equivalence_discipline.fodt
trytond/modules/akademy_matriculation/reports/student_transfer.fodt
trytond/modules/akademy_matriculation/reports/student_transfer_internal.fodt
trytond/modules/akademy_matriculation/security/access_rights_admin.xml
trytond/modules/akademy_matriculation/security/access_rights_direct.xml
trytond/modules/akademy_matriculation/security/access_rights_secret.xml
trytond/modules/akademy_matriculation/security/access_rights_student.xml
trytond/modules/akademy_matriculation/security/access_rights_teacher.xml
trytond/modules/akademy_matriculation/tests/__init__.py
trytond/modules/akademy_matriculation/tests/test_configuration.py
trytond/modules/akademy_matriculation/tests/test_matriculation.py
trytond/modules/akademy_matriculation/tests/test_party.py
trytond/modules/akademy_matriculation/tests/test_report.py
trytond/modules/akademy_matriculation/view/application_avaliation_wizcreate_form.xml
akademy_matriculation-1.1.2.dist-info/METADATA
akademy_matriculation-1.1.2.dist-info/WHEEL
akademy_matriculation-1.1.2.dist-info/licenses/LICENSE
akademy_matriculation-1.1.2.dist-info/RECORD
